setup.py
NLP_Modeller/NLP_Modeller.py
NLP_Modeller/__init__.py
NLP_Modeller.egg-info/PKG-INFO
NLP_Modeller.egg-info/SOURCES.txt
NLP_Modeller.egg-info/dependency_links.txt
NLP_Modeller.egg-info/not-zip-safe
NLP_Modeller.egg-info/top_level.txt