Metadata-Version: 1.0
Name: NLP-Modeller
Version: 0.1
Summary: Quick NLP modelling
Home-page: UNKNOWN
Author: Rakan Alkheliwi
Author-email: rmamnk@gmail.com
License: UNKNOWN
Platform: UNKNOWN
